verifiably_wsock_secrets_provider/__init__.py
verifiably_wsock_secrets_provider/credentials_provider.py
verifiably_wsock_secrets_provider-0.0.7.dist-info/LICENSE
verifiably_wsock_secrets_provider-0.0.7.dist-info/METADATA
verifiably_wsock_secrets_provider-0.0.7.dist-info/WHEEL
verifiably_wsock_secrets_provider-0.0.7.dist-info/top_level.txt
verifiably_wsock_secrets_provider-0.0.7.dist-info/RECORD
