Metadata-Version: 2.1
Name: verifiably-wsock-secrets-provider
Version: 0.0.7
Summary: Secrets provider that communicates with trusted execution environments over web sockets.
Home-page: https://github.com/verifiably/wsock-secrets-provider
Author: Verifiably
Author-email: contact@verifiably.com
License: UNKNOWN
Keywords: python,web-socket,credentials
Platform: UNKNOWN
Classifier: Intended Audience :: Developers
Classifier: Programming Language :: Python :: 3
Classifier: Operating System :: OS Independent
Requires-Python: >=3.8
Requires-Dist: boto3
Requires-Dist: cbor2 (==5.2.0)
Requires-Dist: cose (==0.9.dev2)
Requires-Dist: cryptography (==3.2.1)
Requires-Dist: pyOpenSSL (==19.1.0)
Requires-Dist: pycryptodome (==3.9.9)
Requires-Dist: rel
Requires-Dist: verifiably-checker (==0.0.3)
Requires-Dist: websocket-client
